pysugg/__init__.py
pysugg/exception_catcher.py
pysugg/exception_executors/__init__.py
pysugg/exception_executors/exception_executor.py
pysugg/exception_executors/module_suggest_executor.py
pysugg/exception_executors/pypi_search_executor.py
pysugg/modules_manager/__init__.py
pysugg/modules_manager/modules_manager.py
pysugg-0.0.15.dist-info/LICENSE
pysugg-0.0.15.dist-info/METADATA
pysugg-0.0.15.dist-info/WHEEL
pysugg-0.0.15.dist-info/top_level.txt
pysugg-0.0.15.dist-info/RECORD
