Metadata-Version: 2.1
Name: pysugg
Version: 0.0.15
Summary: A package that can give you some code suggestions when exceptions occurred.
Home-page: https://github.com/bitekong/pysugg
Author: bitekong
Author-email: btk@qq.com
License: UNKNOWN
Project-URL: Bug Tracker, https://github.com/bitekong/pysugg/issues
Platform: UNKNOWN
Classifier: Programming Language :: Python :: 3
Classifier: License :: OSI Approved :: MIT License
Classifier: Operating System :: OS Independent
Requires-Python: >=3.6
License-File: LICENSE
